<VideoStream timebaseNumerator="1" timebaseDenomenator="90000">
<Group pts="0" duration="111111" size="4062" />
<Group pts="111111" duration="390390" size="388068" />
<Group pts="501501" duration="609609" size="663719" />
<Group pts="1111110" duration="639639" size="1042759" />
<Group pts="1750749" duration="846846" size="1719230" />
<Group pts="2597595" duration="630630" size="1433570" />
<Group pts="3228225" duration="192192" size="348869" />
<Group pts="3420417" duration="423423" size="924743" />
<Group pts="3843840" duration="450450" size="879456" />
<Group pts="4294290" duration="186186" size="264838" />
<Group pts="4480476" duration="777777" size="1974597" />
<Group pts="5258253" duration="423423" size="677352" />
<Group pts="5681676" duration="282282" size="546166" />
<Group pts="5963958" duration="150150" size="478767" />
<Group pts="6114108" duration="189189" size="382148" />
<Group pts="6303297" duration="513513" size="1217808" />
<Group pts="6816810" duration="846846" size="1044769" />
<Group pts="7663656" duration="606606" size="1420335" />
<Group pts="8270262" duration="669669" size="1645183" />
<Group pts="8939931" duration="240240" size="345134" />
<Group pts="9180171" duration="492492" size="753000" />
<Group pts="9672663" duration="315315" size="510277" />
<Group pts="9987978" duration="171171" size="266917" />
<Group pts="10159149" duration="723723" size="1199450" />
<Group pts="10882872" duration="249249" size="269788" />
<Group pts="11132121" duration="309309" size="1943809" />
<Group pts="11441430" duration="198198" size="1499828" />
<Group pts="11639628" duration="387387" size="627439" />
<Group pts="12027015" duration="366366" size="504475" />
<Group pts="12393381" duration="132132" size="459161" />
<Group pts="12525513" duration="900900" size="3149174" />
<Group pts="13426413" duration="819819" size="2286699" />
<Group pts="14246232" duration="360360" size="832011" />
<Group pts="14606592" duration="426426" size="1338366" />
<Group pts="15033018" duration="165165" size="277398" />
<Group pts="15198183" duration="156156" size="509099" />
<Group pts="15354339" duration="423423" size="1156536" />
<Group pts="15777762" duration="195195" size="683281" />
<Group pts="15972957" duration="261261" size="496688" />
<Group pts="16234218" duration="96096" size="175445" />
<Group pts="16330314" duration="708708" size="1801294" />
<Group pts="17039022" duration="102102" size="270097" />
<Group pts="17141124" duration="381381" size="1009712" />
<Group pts="17522505" duration="534534" size="1653141" />
<Group pts="18057039" duration="465465" size="775201" />
<Group pts="18522504" duration="384384" size="287671" />
<Group pts="18906888" duration="471471" size="985503" />
<Group pts="19378359" duration="264264" size="648604" />
<Group pts="19642623" duration="261261" size="244586" />
<Group pts="19903884" duration="900900" size="1957280" />
<Group pts="20804784" duration="900900" size="2362774" />
<Group pts="21705684" duration="486486" size="1201848" />
<Group pts="22192170" duration="690690" size="1368417" />
<Group pts="22882860" duration="900900" size="1327942" />
<Group pts="23783760" duration="522522" size="1001988" />
<Group pts="24306282" duration="228228" size="240517" />
<Group pts="24534510" duration="900900" size="1513109" />
<Group pts="25435410" duration="900900" size="1753851" />
<Group pts="26336310" duration="885885" size="2020931" />
<Group pts="27222195" duration="657657" size="942863" />
<Group pts="27879852" duration="576576" size="893319" />
<Group pts="28456428" duration="606606" size="1116154" />
<Group pts="29063034" duration="135135" size="180608" />
<Group pts="29198169" duration="495495" size="797435" />
<Group pts="29693664" duration="750750" size="1859723" />
<Group pts="30444414" duration="900900" size="1709298" />
<Group pts="31345314" duration="699699" size="1067604" />
<Group pts="32045013" duration="288288" size="554055" />
<Group pts="32333301" duration="699699" size="1566088" />
<Group pts="33033000" duration="297297" size="390021" />
<Group pts="33330297" duration="900900" size="1786590" />
<Group pts="34231197" duration="729729" size="1236244" />
<Group pts="34960926" duration="261261" size="528105" />
<Group pts="35222187" duration="642642" size="1491279" />
<Group pts="35864829" duration="348348" size="589390" />
<Group pts="36213177" duration="447447" size="590790" />
<Group pts="36660624" duration="153153" size="241642" />
<Group pts="36813777" duration="153153" size="250026" />
<Group pts="36966930" duration="441441" size="533692" />
<Group pts="37408371" duration="900900" size="1727860" />
<Group pts="38309271" duration="900900" size="2107863" />
<Group pts="39210171" duration="900900" size="1924643" />
<Group pts="40111071" duration="243243" size="391155" />
<Group pts="40354314" duration="336336" size="589199" />
<Group pts="40690650" duration="864864" size="1617128" />
<Group pts="41555514" duration="900900" size="2096234" />
<Group pts="42456414" duration="351351" size="697300" />
<Group pts="42807765" duration="405405" size="821979" />
<Group pts="43213170" duration="264264" size="516676" />
<Group pts="43477434" duration="444444" size="1280649" />
<Group pts="43921878" duration="153153" size="351530" />
<Group pts="44075031" duration="285285" size="715170" />
<Group pts="44360316" duration="246246" size="620745" />
<Group pts="44606562" duration="900900" size="2043926" />
<Group pts="45507462" duration="129129" size="234085" />
<Group pts="45636591" duration="342342" size="708366" />
<Group pts="45978933" duration="270270" size="500140" />
<Group pts="46249203" duration="267267" size="491891" />
<Group pts="46516470" duration="654654" size="1008443" />
<Group pts="47171124" duration="312312" size="657946" />
<Group pts="47483436" duration="900900" size="1755994" />
<Group pts="48384336" duration="93093" size="241554" />
<Group pts="48477429" duration="351351" size="580798" />
<Group pts="48828780" duration="711711" size="1247379" />
<Group pts="49540491" duration="357357" size="1060896" />
<Group pts="49897848" duration="258258" size="692107" />
<Group pts="50156106" duration="273273" size="595189" />
<Group pts="50429379" duration="315315" size="549764" />
<Group pts="50744694" duration="375375" size="718116" />
<Group pts="51120069" duration="465465" size="666251" />
<Group pts="51585534" duration="237237" size="468335" />
<Group pts="51822771" duration="108108" size="277323" />
<Group pts="51930879" duration="798798" size="1415571" />
<Group pts="52729677" duration="318318" size="417072" />
<Group pts="53047995" duration="639639" size="1436671" />
<Group pts="53687634" duration="882882" size="1085093" />
<Group pts="54570516" duration="600600" size="1179280" />
<Group pts="55171116" duration="120120" size="164335" />
<Group pts="55291236" duration="474474" size="780740" />
<Group pts="55765710" duration="186186" size="339198" />
<Group pts="55951896" duration="459459" size="1069540" />
<Group pts="56411355" duration="183183" size="283110" />
<Group pts="56594538" duration="114114" size="232192" />
<Group pts="56708652" duration="555555" size="1276246" />
<Group pts="57264207" duration="168168" size="247579" />
<Group pts="57432375" duration="114114" size="204504" />
<Group pts="57546489" duration="900900" size="2089546" />
<Group pts="58447389" duration="357357" size="855415" />
<Group pts="58804746" duration="681681" size="1401216" />
<Group pts="59486427" duration="180180" size="302436" />
<Group pts="59666607" duration="900900" size="1914752" />
<Group pts="60567507" duration="174174" size="315621" />
<Group pts="60741681" duration="183183" size="458641" />
<Group pts="60924864" duration="156156" size="205757" />
<Group pts="61081020" duration="111111" size="119423" />
<Group pts="61192131" duration="255255" size="497650" />
<Group pts="61447386" duration="522522" size="723335" />
<Group pts="61969908" duration="231231" size="460871" />
<Group pts="62201139" duration="648648" size="1347977" />
<Group pts="62849787" duration="372372" size="700641" />
<Group pts="63222159" duration="159159" size="285497" />
<Group pts="63381318" duration="900900" size="2535191" />
<Group pts="64282218" duration="483483" size="733750" />
<Group pts="64765701" duration="192192" size="469997" />
<Group pts="64957893" duration="870870" size="1415710" />
<Group pts="65828763" duration="147147" size="373524" />
<Group pts="65975910" duration="156156" size="326878" />
<Group pts="66132066" duration="378378" size="880957" />
<Group pts="66510444" duration="381381" size="687142" />
<Group pts="66891825" duration="318318" size="658411" />
<Group pts="67210143" duration="315315" size="790731" />
<Group pts="67525458" duration="543543" size="1151127" />
<Group pts="68069001" duration="219219" size="408963" />
<Group pts="68288220" duration="132132" size="259132" />
<Group pts="68420352" duration="414414" size="705508" />
<Group pts="68834766" duration="900900" size="1819424" />
<Group pts="69735666" duration="129129" size="200579" />
<Group pts="69864795" duration="900900" size="1691017" />
<Group pts="70765695" duration="342342" size="629403" />
<Group pts="71108037" duration="135135" size="128600" />
<Group pts="71243172" duration="900900" size="934098" />
<Group pts="72144072" duration="900900" size="1139051" />
<Group pts="73044972" duration="195195" size="279498" />
<Group pts="73240167" duration="285285" size="435136" />
<Group pts="73525452" duration="900900" size="2036188" />
<Group pts="74426352" duration="330330" size="512002" />
<Group pts="74756682" duration="432432" size="983161" />
<Group pts="75189114" duration="627627" size="1308466" />
<Group pts="75816741" duration="198198" size="369807" />
<Group pts="76014939" duration="708708" size="956432" />
<Group pts="76723647" duration="336336" size="691537" />
<Group pts="77059983" duration="900900" size="2447338" />
<Group pts="77960883" duration="417417" size="895338" />
<Group pts="78378300" duration="207207" size="427048" />
<Group pts="78585507" duration="111111" size="242933" />
<Group pts="78696618" duration="381381" size="658153" />
<Group pts="79077999" duration="285285" size="588421" />
<Group pts="79363284" duration="474474" size="1126655" />
<Group pts="79837758" duration="432432" size="870202" />
<Group pts="80270190" duration="387387" size="841139" />
<Group pts="80657577" duration="156156" size="280412" />
<Group pts="80813733" duration="660660" size="1002260" />
<Group pts="81474393" duration="168168" size="333927" />
<Group pts="81642561" duration="255255" size="515847" />
<Group pts="81897816" duration="702702" size="1523319" />
<Group pts="82600518" duration="324324" size="616824" />
<Group pts="82924842" duration="144144" size="291394" />
<Group pts="83068986" duration="147147" size="411125" />
<Group pts="83216133" duration="312312" size="647401" />
<Group pts="83528445" duration="441441" size="814891" />
<Group pts="83969886" duration="543543" size="1398637" />
<Group pts="84513429" duration="696696" size="1092571" />
<Group pts="85210125" duration="213213" size="338514" />
<Group pts="85423338" duration="183183" size="320697" />
<Group pts="85606521" duration="129129" size="421064" />
<Group pts="85735650" duration="867867" size="1545142" />
<Group pts="86603517" duration="309309" size="523797" />
<Group pts="86912826" duration="594594" size="1187002" />
<Group pts="87507420" duration="294294" size="515383" />
<Group pts="87801714" duration="630630" size="1599404" />
<Group pts="88432344" duration="279279" size="598159" />
<Group pts="88711623" duration="144144" size="204098" />
<Group pts="88855767" duration="204204" size="378498" />
<Group pts="89059971" duration="318318" size="476270" />
<Group pts="89378289" duration="315315" size="556712" />
<Group pts="89693604" duration="195195" size="237175" />
<Group pts="89888799" duration="240240" size="456379" />
<Group pts="90129039" duration="459459" size="1098003" />
<Group pts="90588498" duration="900900" size="1792967" />
<Group pts="91489398" duration="297297" size="494574" />
<Group pts="91786695" duration="900900" size="2191592" />
<Group pts="92687595" duration="462462" size="846877" />
<Group pts="93150057" duration="672672" size="1000192" />
<Group pts="93822729" duration="537537" size="835726" />
<Group pts="94360266" duration="435435" size="632039" />
<Group pts="94795701" duration="120120" size="194232" />
<Group pts="94915821" duration="294294" size="451001" />
<Group pts="95210115" duration="900900" size="1481445" />
<Group pts="96111015" duration="900900" size="1975430" />
<Group pts="97011915" duration="93093" size="208768" />
<Group pts="97105008" duration="393393" size="570866" />
<Group pts="97498401" duration="597597" size="781871" />
<Group pts="98095998" duration="240240" size="545647" />
<Group pts="98336238" duration="900900" size="1381909" />
<Group pts="99237138" duration="348348" size="442502" />
<Group pts="99585486" duration="588588" size="1099477" />
<Group pts="100174074" duration="165165" size="332428" />
<Group pts="100339239" duration="261261" size="585033" />
<Group pts="100600500" duration="471471" size="815550" />
<Group pts="101071971" duration="171171" size="329247" />
<Group pts="101243142" duration="186186" size="303863" />
<Group pts="101429328" duration="240240" size="434533" />
<Group pts="101669568" duration="357357" size="458536" />
<Group pts="102026925" duration="459459" size="776609" />
<Group pts="102486384" duration="105105" size="181975" />
<Group pts="102591489" duration="201201" size="358336" />
<Group pts="102792690" duration="123123" size="265445" />
<Group pts="102915813" duration="495495" size="1047429" />
<Group pts="103411308" duration="543543" size="815430" />
<Group pts="103954851" duration="201201" size="237134" />
<Group pts="104156052" duration="900900" size="1379117" />
<Group pts="105056952" duration="183183" size="253245" />
<Group pts="105240135" duration="570570" size="1222210" />
<Group pts="105810705" duration="747747" size="1264351" />
<Group pts="106558452" duration="201201" size="480701" />
<Group pts="106759653" duration="402402" size="798337" />
<Group pts="107162055" duration="900900" size="1669334" />
<Group pts="108062955" duration="273273" size="464925" />
<Group pts="108336228" duration="93093" size="138566" />
<Group pts="108429321" duration="546546" size="940183" />
<Group pts="108975867" duration="264264" size="328402" />
<Group pts="109240131" duration="471471" size="634491" />
<Group pts="109711602" duration="300300" size="328533" />
<Group pts="110011902" duration="342342" size="492159" />
<Group pts="110354244" duration="900900" size="1513612" />
<Group pts="111255144" duration="576576" size="715528" />
<Group pts="111831720" duration="141141" size="166287" />
<Group pts="111972861" duration="294294" size="647418" />
<Group pts="112267155" duration="465465" size="1068393" />
<Group pts="112732620" duration="339339" size="290884" />
<Group pts="113071959" duration="510510" size="978991" />
<Group pts="113582469" duration="153153" size="217390" />
<Group pts="113735622" duration="606606" size="1102864" />
<Group pts="114342228" duration="201201" size="401882" />
<Group pts="114543429" duration="333333" size="457215" />
<Group pts="114876762" duration="900900" size="1583739" />
<Group pts="115777662" duration="900900" size="1228523" />
<Group pts="116678562" duration="378378" size="619991" />
<Group pts="117056940" duration="900900" size="1010447" />
<Group pts="117957840" duration="900900" size="842314" />
<Group pts="118858740" duration="900900" size="1000458" />
<Group pts="119759640" duration="900900" size="1217087" />
<Group pts="120660540" duration="786786" size="1074883" />
<Group pts="121447326" duration="153153" size="306278" />
<Group pts="121600479" duration="144144" size="383151" />
<Group pts="121744623" duration="342342" size="820142" />
<Group pts="122086965" duration="456456" size="1149340" />
<Group pts="122543421" duration="603603" size="619175" />
<Group pts="123147024" duration="600600" size="1257402" />
<Group pts="123747624" duration="552552" size="1180365" />
<Group pts="124300176" duration="258258" size="691103" />
<Group pts="124558434" duration="381381" size="841082" />
<Group pts="124939815" duration="150150" size="303235" />
<Group pts="125089965" duration="123123" size="272127" />
</VideoStream>
